[{"la":65.427425,"lo":25.560118,"n":"","t":"man_made=tar_kiln"},{"la":65.430569,"lo":25.562592,"n":"","t":"historic=archaeological_site"},{"la":65.434351,"lo":25.564108,"n":"","t":"historic=archaeological_site"},{"la":65.432503,"lo":25.512056,"n":"","t":"historic=archaeological_site"},{"la":65.426359,"lo":25.563253,"n":"","t":"historic=archaeological_site"},{"la":65.432756,"lo":25.566135,"n":"","t":"historic=archaeological_site"},{"la":65.431385,"lo":25.535394,"n":"","t":"historic=archaeological_site"},{"la":65.436469,"lo":25.538672,"n":"","t":"natural=water"},{"la":65.436437,"lo":25.538469,"n":"","t":"natural=water"},{"la":65.427408,"lo":25.562014,"n":"","t":"natural=water"},{"la":65.427738,"lo":25.559429,"n":"","t":"natural=water"},{"la":65.427402,"lo":25.561985,"n":"","t":"natural=water"},{"la":65.427746,"lo":25.559422,"n":"","t":"natural=water"}]