[{"la":60.560233,"lo":23.967707,"n":"","t":"tourism=viewpoint"},{"la":60.564799,"lo":23.966743,"n":"","t":"amenity=boat_storage"},{"la":60.56449,"lo":23.966538,"n":"","t":"tourism=viewpoint"},{"la":60.564601,"lo":23.96656,"n":"","t":"amenity=waste_basket"},{"la":60.564522,"lo":23.966699,"n":"","t":"leisure=firepit"},{"la":60.55571,"lo":23.993895,"n":"Tytylampi","t":"natural=water"},{"la":60.555715,"lo":23.993861,"n":"Tytylampi","t":"natural=water"},{"la":60.561546,"lo":23.928974,"n":"Kivijärvi","t":"natural=water"},{"la":60.548715,"lo":23.940767,"n":"Heinäistenjärvi","t":"natural=water"},{"la":60.55092,"lo":23.912324,"n":"Kyläntakanen","t":"natural=water"},{"la":60.561539,"lo":23.928915,"n":"Kivijärvi","t":"natural=water"},{"la":60.548705,"lo":23.940724,"n":"Heinäistenjärvi","t":"natural=water"},{"la":60.550872,"lo":23.912175,"n":"Kyläntakanen","t":"natural=water"},{"la":60.564725,"lo":23.96422,"n":"","t":"amenity=parking"},{"la":60.564725,"lo":23.96422,"n":"","t":"amenity=parking"},{"la":60.564013,"lo":23.987906,"n":"Vahermajärvi","t":"natural=water"},{"la":60.552708,"lo":23.975075,"n":"","t":"natural=water"},{"la":60.552705,"lo":23.975034,"n":"","t":"natural=water"},{"la":60.543851,"lo":23.972871,"n":"","t":"natural=wood"},{"la":60.546575,"lo":23.985027,"n":"","t":"natural=wood"},{"la":60.556558,"lo":23.993143,"n":"","t":"leisure=nature_reserve"},{"la":60.543829,"lo":23.972865,"n":"","t":"natural=wood"},{"la":60.546586,"lo":23.984998,"n":"","t":"natural=wood"},{"la":60.556566,"lo":23.993074,"n":"","t":"leisure=nature_reserve"},{"la":60.56443,"lo":23.939769,"n":"","t":"natural=wetland"},{"la":60.55695,"lo":23.917514,"n":"","t":"leisure=pitch"},{"la":60.552905,"lo":23.943242,"n":"","t":"leisure=pitch"},{"la":60.564438,"lo":23.939759,"n":"","t":"natural=wetland"},{"la":60.556884,"lo":23.917501,"n":"","t":"leisure=pitch"},{"la":60.552831,"lo":23.943091,"n":"","t":"leisure=pitch"}]