[{"la":61.436329,"lo":29.208883,"n":"","t":"man_made=mast"},{"la":61.42717,"lo":29.240012,"n":"","t":"historic=archaeological_site"},{"la":61.425676,"lo":29.240959,"n":"","t":"historic=archaeological_site"},{"la":61.421096,"lo":29.261496,"n":"","t":"natural=wood"},{"la":61.432062,"lo":29.212823,"n":"","t":"natural=wood"},{"la":61.420979,"lo":29.261296,"n":"","t":"natural=wood"},{"la":61.432052,"lo":29.212601,"n":"","t":"natural=wood"},{"la":61.419463,"lo":29.263895,"n":"Mäntylampi","t":"natural=water"},{"la":61.42259,"lo":29.260318,"n":"Likolampi","t":"natural=water"},{"la":61.418558,"lo":29.255189,"n":"","t":"natural=wetland"},{"la":61.418364,"lo":29.257819,"n":"","t":"natural=bare_rock"},{"la":61.420675,"lo":29.256487,"n":"","t":"natural=bare_rock"},{"la":61.418197,"lo":29.249471,"n":"","t":"natural=wetland"},{"la":61.420002,"lo":29.249056,"n":"","t":"natural=wetland"},{"la":61.419424,"lo":29.251733,"n":"","t":"natural=wetland"},{"la":61.42112,"lo":29.256219,"n":"","t":"natural=bare_rock"},{"la":61.424115,"lo":29.258601,"n":"","t":"natural=wetland"},{"la":61.435026,"lo":29.258691,"n":"","t":"natural=bare_rock"},{"la":61.435462,"lo":29.250275,"n":"","t":"natural=bare_rock"},{"la":61.434609,"lo":29.250382,"n":"","t":"natural=wetland"},{"la":61.428568,"lo":29.26753,"n":"","t":"natural=wetland"},{"la":61.428526,"lo":29.260461,"n":"","t":"natural=bare_rock"},{"la":61.4324,"lo":29.264304,"n":"","t":"natural=bare_rock"},{"la":61.43573,"lo":29.266484,"n":"","t":"natural=bare_rock"},{"la":61.434952,"lo":29.26161,"n":"","t":"natural=bare_rock"},{"la":61.436555,"lo":29.26054,"n":"","t":"natural=bare_rock"},{"la":61.435355,"lo":29.262999,"n":"","t":"natural=wetland"},{"la":61.437358,"lo":29.266501,"n":"","t":"natural=bare_rock"},{"la":61.437621,"lo":29.261449,"n":"","t":"natural=bare_rock"},{"la":61.438235,"lo":29.258281,"n":"","t":"natural=wetland"},{"la":61.419463,"lo":29.263893,"n":"Mäntylampi","t":"natural=water"},{"la":61.42259,"lo":29.260318,"n":"Likolampi","t":"natural=water"},{"la":61.422602,"lo":29.260098,"n":"","t":"natural=wetland"},{"la":61.418572,"lo":29.255119,"n":"","t":"natural=wetland"},{"la":61.418356,"lo":29.257804,"n":"","t":"natural=bare_rock"},{"la":61.420679,"lo":29.256484,"n":"","t":"natural=bare_rock"},{"la":61.420072,"lo":29.256422,"n":"","t":"natural=wetland"},{"la":61.418171,"lo":29.249442,"n":"","t":"natural=wetland"},{"la":61.419983,"lo":29.249028,"n":"","t":"natural=wetland"},{"la":61.419392,"lo":29.251706,"n":"","t":"natural=wetland"},{"la":61.421117,"lo":29.25618,"n":"","t":"natural=bare_rock"},{"la":61.424094,"lo":29.258593,"n":"","t":"natural=wetland"},{"la":61.435017,"lo":29.258671,"n":"","t":"natural=bare_rock"},{"la":61.435462,"lo":29.250275,"n":"","t":"natural=bare_rock"},{"la":61.434601,"lo":29.25036,"n":"","t":"natural=wetland"},{"la":61.428576,"lo":29.267507,"n":"","t":"natural=wetland"},{"la":61.428531,"lo":29.260461,"n":"","t":"natural=bare_rock"},{"la":61.432387,"lo":29.264299,"n":"","t":"natural=bare_rock"},{"la":61.435721,"lo":29.266479,"n":"","t":"natural=bare_rock"},{"la":61.434952,"lo":29.26161,"n":"","t":"natural=bare_rock"},{"la":61.436535,"lo":29.260514,"n":"","t":"natural=bare_rock"},{"la":61.435315,"lo":29.262955,"n":"","t":"natural=wetland"},{"la":61.437366,"lo":29.26649,"n":"","t":"natural=bare_rock"},{"la":61.437611,"lo":29.261444,"n":"","t":"natural=bare_rock"},{"la":61.438198,"lo":29.258227,"n":"","t":"natural=wetland"},{"la":61.420551,"lo":29.256571,"n":"","t":"natural=cliff"},{"la":61.419133,"lo":29.257249,"n":"","t":"natural=cliff"},{"la":61.418971,"lo":29.250406,"n":"","t":"natural=cliff"},{"la":61.435396,"lo":29.250125,"n":"","t":"natural=cliff"},{"la":61.427996,"lo":29.26082,"n":"","t":"natural=cliff"},{"la":61.428309,"lo":29.25896,"n":"","t":"natural=cliff"},{"la":61.434796,"lo":29.260869,"n":"","t":"natural=cliff"},{"la":61.424486,"lo":29.216889,"n":"","t":"natural=bare_rock"},{"la":61.422602,"lo":29.219644,"n":"","t":"natural=water"},{"la":61.422639,"lo":29.219926,"n":"","t":"natural=wetland"},{"la":61.423617,"lo":29.219492,"n":"","t":"natural=wetland"},{"la":61.42262,"lo":29.220197,"n":"","t":"natural=wetland"},{"la":61.423638,"lo":29.226602,"n":"","t":"natural=wetland"},{"la":61.431251,"lo":29.228218,"n":"","t":"natural=bare_rock"},{"la":61.429886,"lo":29.227662,"n":"","t":"natural=bare_rock"},{"la":61.429713,"lo":29.224655,"n":"","t":"natural=wetland"},{"la":61.429481,"lo":29.230456,"n":"","t":"natural=wetland"},{"la":61.432653,"lo":29.225752,"n":"","t":"natural=bare_rock"},{"la":61.432899,"lo":29.226374,"n":"","t":"natural=bare_rock"},{"la":61.432327,"lo":29.229871,"n":"","t":"natural=bare_rock"},{"la":61.433668,"lo":29.230411,"n":"","t":"natural=wetland"},{"la":61.432281,"lo":29.228087,"n":"","t":"natural=wetland"},{"la":61.43621,"lo":29.2292,"n":"","t":"natural=bare_rock"},{"la":61.43549,"lo":29.226005,"n":"","t":"natural=wetland"},{"la":61.437438,"lo":29.222906,"n":"","t":"natural=wetland"},{"la":61.431435,"lo":29.188895,"n":"","t":"natural=bare_rock"},{"la":61.431485,"lo":29.185897,"n":"","t":"natural=bare_rock"},{"la":61.432055,"lo":29.187807,"n":"","t":"natural=bare_rock"},{"la":61.431137,"lo":29.186206,"n":"","t":"natural=bare_rock"},{"la":61.43369,"lo":29.187169,"n":"","t":"natural=bare_rock"},{"la":61.433459,"lo":29.190685,"n":"","t":"natural=bare_rock"},{"la":61.435069,"lo":29.187332,"n":"","t":"natural=bare_rock"},{"la":61.43374,"lo":29.191463,"n":"","t":"natural=bare_rock"},{"la":61.434792,"lo":29.192131,"n":"","t":"natural=bare_rock"},{"la":61.436497,"lo":29.194354,"n":"","t":"natural=bare_rock"},{"la":61.43611,"lo":29.192912,"n":"","t":"natural=bare_rock"},{"la":61.437383,"lo":29.193245,"n":"","t":"natural=bare_rock"},{"la":61.436775,"lo":29.193122,"n":"","t":"natural=bare_rock"},{"la":61.436836,"lo":29.194774,"n":"","t":"natural=bare_rock"},{"la":61.436111,"lo":29.186741,"n":"","t":"natural=bare_rock"},{"la":61.435279,"lo":29.191759,"n":"","t":"natural=bare_rock"},{"la":61.43734,"lo":29.191795,"n":"","t":"natural=bare_rock"},{"la":61.43619,"lo":29.181015,"n":"","t":"natural=bare_rock"},{"la":61.437454,"lo":29.184036,"n":"","t":"natural=bare_rock"},{"la":61.437528,"lo":29.181348,"n":"","t":"natural=bare_rock"},{"la":61.437825,"lo":29.182017,"n":"","t":"natural=wetland"},{"la":61.432254,"lo":29.194379,"n":"","t":"natural=wetland"},{"la":61.431666,"lo":29.203324,"n":"","t":"natural=bare_rock"},{"la":61.430175,"lo":29.201924,"n":"","t":"natural=bare_rock"},{"la":61.430883,"lo":29.201255,"n":"","t":"natural=bare_rock"},{"la":61.431272,"lo":29.197196,"n":"","t":"leisure=pitch"},{"la":61.431384,"lo":29.202759,"n":"","t":"natural=bare_rock"},{"la":61.4286,"lo":29.219856,"n":"","t":"natural=wetland"},{"la":61.427869,"lo":29.21558,"n":"","t":"natural=bare_rock"},{"la":61.433495,"lo":29.221133,"n":"","t":"natural=wetland"},{"la":61.436714,"lo":29.221462,"n":"","t":"natural=wetland"},{"la":61.432488,"lo":29.201776,"n":"","t":"natural=bare_rock"},{"la":61.432336,"lo":29.202335,"n":"","t":"natural=bare_rock"},{"la":61.4325,"lo":29.202536,"n":"","t":"natural=bare_rock"},{"la":61.433134,"lo":29.201636,"n":"","t":"natural=bare_rock"},{"la":61.433892,"lo":29.200652,"n":"","t":"natural=bare_rock"},{"la":61.434816,"lo":29.202154,"n":"","t":"natural=wetland"},{"la":61.435014,"lo":29.200292,"n":"","t":"natural=bare_rock"},{"la":61.434764,"lo":29.199591,"n":"","t":"natural=bare_rock"},{"la":61.432279,"lo":29.204703,"n":"","t":"natural=wetland"},{"la":61.432026,"lo":29.208459,"n":"","t":"natural=wetland"},{"la":61.435596,"lo":29.202194,"n":"","t":"natural=wetland"},{"la":61.435494,"lo":29.204498,"n":"","t":"natural=bare_rock"},{"la":61.436983,"lo":29.210004,"n":"","t":"natural=bare_rock"},{"la":61.437017,"lo":29.208772,"n":"","t":"natural=bare_rock"},{"la":61.436305,"lo":29.199614,"n":"Pikilampi","t":"natural=water"},{"la":61.43539,"lo":29.198346,"n":"","t":"natural=bare_rock"},{"la":61.435807,"lo":29.19797,"n":"","t":"natural=bare_rock"},{"la":61.436682,"lo":29.201624,"n":"","t":"natural=bare_rock"},{"la":61.437373,"lo":29.20184,"n":"","t":"natural=bare_rock"},{"la":61.436712,"lo":29.198309,"n":"","t":"natural=wetland"},{"la":61.432852,"lo":29.202923,"n":"","t":"natural=bare_rock"},{"la":61.432267,"lo":29.199896,"n":"","t":"natural=bare_rock"},{"la":61.438314,"lo":29.202097,"n":"","t":"natural=bare_rock"},{"la":61.43786,"lo":29.201991,"n":"","t":"natural=bare_rock"},{"la":61.438235,"lo":29.20319,"n":"","t":"natural=wetland"},{"la":61.438088,"lo":29.183397,"n":"","t":"natural=bare_rock"},{"la":61.43817,"lo":29.184812,"n":"","t":"natural=bare_rock"},{"la":61.424473,"lo":29.216879,"n":"","t":"natural=bare_rock"},{"la":61.422625,"lo":29.219629,"n":"","t":"natural=water"},{"la":61.422641,"lo":29.219925,"n":"","t":"natural=wetland"},{"la":61.420945,"lo":29.224777,"n":"Sauniemensuo","t":"natural=wetland"},{"la":61.431275,"lo":29.228162,"n":"","t":"natural=bare_rock"},{"la":61.429854,"lo":29.227629,"n":"","t":"natural=bare_rock"},{"la":61.429698,"lo":29.224617,"n":"","t":"natural=wetland"},{"la":61.429459,"lo":29.230361,"n":"","t":"natural=wetland"},{"la":61.432637,"lo":29.225743,"n":"","t":"natural=bare_rock"},{"la":61.432908,"lo":29.226315,"n":"","t":"natural=bare_rock"},{"la":61.432306,"lo":29.229837,"n":"","t":"natural=bare_rock"},{"la":61.433668,"lo":29.230411,"n":"","t":"natural=wetland"},{"la":61.432256,"lo":29.228042,"n":"","t":"natural=wetland"},{"la":61.436226,"lo":29.229148,"n":"","t":"natural=bare_rock"},{"la":61.435504,"lo":29.225992,"n":"","t":"natural=wetland"},{"la":61.437456,"lo":29.222891,"n":"","t":"natural=wetland"},{"la":61.431463,"lo":29.188838,"n":"","t":"natural=bare_rock"},{"la":61.431472,"lo":29.185893,"n":"","t":"natural=bare_rock"},{"la":61.432045,"lo":29.187758,"n":"","t":"natural=bare_rock"},{"la":61.431113,"lo":29.186159,"n":"","t":"natural=bare_rock"},{"la":61.433695,"lo":29.187111,"n":"","t":"natural=bare_rock"},{"la":61.433472,"lo":29.190678,"n":"","t":"natural=bare_rock"},{"la":61.435057,"lo":29.187331,"n":"","t":"natural=bare_rock"},{"la":61.433725,"lo":29.191458,"n":"","t":"natural=bare_rock"},{"la":61.435492,"lo":29.191545,"n":"Ojasuo","t":"natural=wetland"},{"la":61.434812,"lo":29.192065,"n":"","t":"natural=bare_rock"},{"la":61.436499,"lo":29.194332,"n":"","t":"natural=bare_rock"},{"la":61.43613,"lo":29.19286,"n":"","t":"natural=bare_rock"},{"la":61.437373,"lo":29.193231,"n":"","t":"natural=bare_rock"},{"la":61.436782,"lo":29.193116,"n":"","t":"natural=bare_rock"},{"la":61.436842,"lo":29.194769,"n":"","t":"natural=bare_rock"},{"la":61.436102,"lo":29.186726,"n":"","t":"natural=bare_rock"},{"la":61.435267,"lo":29.191714,"n":"","t":"natural=bare_rock"},{"la":61.437355,"lo":29.191746,"n":"","t":"natural=bare_rock"},{"la":61.436155,"lo":29.180982,"n":"","t":"natural=bare_rock"},{"la":61.437444,"lo":29.184035,"n":"","t":"natural=bare_rock"},{"la":61.437548,"lo":29.181313,"n":"","t":"natural=bare_rock"},{"la":61.437819,"lo":29.182006,"n":"","t":"natural=wetland"},{"la":61.432262,"lo":29.194335,"n":"","t":"natural=wetland"},{"la":61.431688,"lo":29.203307,"n":"","t":"natural=bare_rock"},{"la":61.430182,"lo":29.201919,"n":"","t":"natural=bare_rock"},{"la":61.4309,"lo":29.201244,"n":"","t":"natural=bare_rock"},{"la":61.431241,"lo":29.197163,"n":"","t":"leisure=pitch"},{"la":61.431416,"lo":29.202721,"n":"","t":"natural=bare_rock"},{"la":61.4286,"lo":29.219856,"n":"","t":"natural=wetland"},{"la":61.427898,"lo":29.215538,"n":"","t":"natural=bare_rock"},{"la":61.43348,"lo":29.221108,"n":"","t":"natural=wetland"},{"la":61.43672,"lo":29.221363,"n":"","t":"natural=wetland"},{"la":61.432488,"lo":29.201776,"n":"","t":"natural=bare_rock"},{"la":61.432315,"lo":29.202317,"n":"","t":"natural=bare_rock"},{"la":61.4325,"lo":29.202536,"n":"","t":"natural=bare_rock"},{"la":61.433124,"lo":29.201623,"n":"","t":"natural=bare_rock"},{"la":61.433877,"lo":29.200642,"n":"","t":"natural=bare_rock"},{"la":61.434806,"lo":29.202143,"n":"","t":"natural=wetland"},{"la":61.435057,"lo":29.200252,"n":"","t":"natural=bare_rock"},{"la":61.434761,"lo":29.199524,"n":"","t":"natural=bare_rock"},{"la":61.432279,"lo":29.204703,"n":"","t":"natural=wetland"},{"la":61.432014,"lo":29.208442,"n":"","t":"natural=wetland"},{"la":61.435596,"lo":29.202194,"n":"","t":"natural=wetland"},{"la":61.435488,"lo":29.204493,"n":"","t":"natural=bare_rock"},{"la":61.436993,"lo":29.209976,"n":"","t":"natural=bare_rock"},{"la":61.437017,"lo":29.208772,"n":"","t":"natural=bare_rock"},{"la":61.436306,"lo":29.199614,"n":"Pikilampi","t":"natural=water"},{"la":61.435382,"lo":29.198337,"n":"","t":"natural=bare_rock"},{"la":61.435794,"lo":29.19797,"n":"","t":"natural=bare_rock"},{"la":61.436661,"lo":29.201604,"n":"","t":"natural=bare_rock"},{"la":61.437362,"lo":29.201837,"n":"","t":"natural=bare_rock"},{"la":61.436722,"lo":29.198261,"n":"","t":"natural=wetland"},{"la":61.432904,"lo":29.20287,"n":"","t":"natural=bare_rock"},{"la":61.432267,"lo":29.199896,"n":"","t":"natural=bare_rock"},{"la":61.438323,"lo":29.202089,"n":"","t":"natural=bare_rock"},{"la":61.43787,"lo":29.201967,"n":"","t":"natural=bare_rock"},{"la":61.438218,"lo":29.203138,"n":"","t":"natural=wetland"},{"la":61.438115,"lo":29.183383,"n":"","t":"natural=bare_rock"},{"la":61.438159,"lo":29.184802,"n":"","t":"natural=bare_rock"},{"la":61.438712,"lo":29.182736,"n":"","t":"natural=bare_rock"},{"la":61.438408,"lo":29.187641,"n":"","t":"natural=bare_rock"},{"la":61.438748,"lo":29.188848,"n":"","t":"natural=bare_rock"},{"la":61.437867,"lo":29.194033,"n":"","t":"natural=wetland"},{"la":61.438034,"lo":29.195576,"n":"","t":"natural=bare_rock"},{"la":61.437702,"lo":29.196114,"n":"","t":"natural=bare_rock"},{"la":61.438709,"lo":29.195629,"n":"","t":"natural=wetland"},{"la":61.437607,"lo":29.19503,"n":"","t":"natural=bare_rock"},{"la":61.438242,"lo":29.191477,"n":"","t":"natural=bare_rock"},{"la":61.417796,"lo":29.243432,"n":"","t":"natural=bare_rock"},{"la":61.419636,"lo":29.246339,"n":"","t":"natural=wetland"},{"la":61.418005,"lo":29.244464,"n":"","t":"natural=wetland"},{"la":61.419968,"lo":29.248732,"n":"","t":"natural=wetland"},{"la":61.41796,"lo":29.247832,"n":"","t":"natural=bare_rock"},{"la":61.427638,"lo":29.2412,"n":"","t":"natural=bare_rock"},{"la":61.433483,"lo":29.246417,"n":"","t":"natural=bare_rock"},{"la":61.433154,"lo":29.242101,"n":"","t":"natural=wetland"},{"la":61.430744,"lo":29.243212,"n":"","t":"natural=wetland"},{"la":61.438719,"lo":29.182727,"n":"","t":"natural=bare_rock"},{"la":61.438397,"lo":29.187634,"n":"","t":"natural=bare_rock"},{"la":61.438748,"lo":29.188848,"n":"","t":"natural=bare_rock"},{"la":61.437888,"lo":29.193962,"n":"","t":"natural=wetland"},{"la":61.438016,"lo":29.195573,"n":"","t":"natural=bare_rock"},{"la":61.437696,"lo":29.196109,"n":"","t":"natural=bare_rock"},{"la":61.438709,"lo":29.195629,"n":"","t":"natural=wetland"},{"la":61.437596,"lo":29.195025,"n":"","t":"natural=bare_rock"},{"la":61.438246,"lo":29.191445,"n":"","t":"natural=bare_rock"},{"la":61.417783,"lo":29.243429,"n":"","t":"natural=bare_rock"},{"la":61.419627,"lo":29.246327,"n":"","t":"natural=wetland"},{"la":61.418005,"lo":29.244464,"n":"","t":"natural=wetland"},{"la":61.419992,"lo":29.248711,"n":"","t":"natural=wetland"},{"la":61.417965,"lo":29.247807,"n":"","t":"natural=bare_rock"},{"la":61.4276,"lo":29.241131,"n":"","t":"natural=bare_rock"},{"la":61.43348,"lo":29.246416,"n":"","t":"natural=bare_rock"},{"la":61.433061,"lo":29.238999,"n":"Torvisensuo","t":"natural=wetland"},{"la":61.435153,"lo":29.248909,"n":"","t":"natural=wetland"},{"la":61.430751,"lo":29.243176,"n":"","t":"natural=wetland"},{"la":61.429481,"lo":29.199091,"n":"","t":"man_made=embankment"},{"la":61.431398,"lo":29.196822,"n":"","t":"man_made=embankment"},{"la":61.434889,"lo":29.200166,"n":"","t":"natural=cliff"},{"la":61.429966,"lo":29.228145,"n":"","t":"natural=cliff"},{"la":61.431254,"lo":29.231205,"n":"","t":"natural=cliff"},{"la":61.431619,"lo":29.231304,"n":"","t":"natural=cliff"},{"la":61.438411,"lo":29.229583,"n":"","t":"natural=cliff"},{"la":61.431785,"lo":29.203135,"n":"","t":"natural=cliff"},{"la":61.431,"lo":29.201113,"n":"","t":"natural=cliff"},{"la":61.431469,"lo":29.215096,"n":"","t":"natural=cliff"},{"la":61.432986,"lo":29.201686,"n":"","t":"natural=cliff"},{"la":61.432769,"lo":29.202928,"n":"","t":"natural=cliff"},{"la":61.4358,"lo":29.202309,"n":"","t":"natural=cliff"},{"la":61.432107,"lo":29.200426,"n":"","t":"natural=cliff"},{"la":61.437454,"lo":29.202184,"n":"","t":"natural=cliff"},{"la":61.437709,"lo":29.202259,"n":"","t":"natural=cliff"},{"la":61.438692,"lo":29.190827,"n":"","t":"natural=cliff"},{"la":61.438008,"lo":29.192814,"n":"","t":"natural=cliff"},{"la":61.426271,"lo":29.240649,"n":"","t":"natural=cliff"},{"la":61.42704,"lo":29.239946,"n":"","t":"natural=cliff"},{"la":61.430551,"lo":29.235864,"n":"","t":"natural=cliff"},{"la":61.425945,"lo":29.242329,"n":"","t":"natural=cliff"},{"la":61.435483,"lo":29.249852,"n":"","t":"natural=cliff"},{"la":61.421345,"lo":29.217176,"n":"Hiekkalahti","t":"natural=bay"},{"la":61.422902,"lo":29.217694,"n":"Kalatoksenlahti","t":"natural=bay"},{"la":61.426274,"lo":29.215177,"n":"Simolansalmi","t":"natural=strait"},{"la":61.418705,"lo":29.229674,"n":"Torsanlahti","t":"natural=bay"},{"la":61.434776,"lo":29.25676,"n":"Hytinlahti","t":"natural=bay"},{"la":61.43447,"lo":29.250994,"n":"Ravannonlahti","t":"natural=bay"},{"la":61.427372,"lo":29.250121,"n":"Pieni-Torsa","t":"natural=water"},{"la":61.423497,"lo":29.25652,"n":"Pajulahti","t":"natural=bay"},{"la":61.427479,"lo":29.224151,"n":"","t":"man_made=pier"}]